setup.py
urbandefinition.py
urbandefinition.egg-info/PKG-INFO
urbandefinition.egg-info/SOURCES.txt
urbandefinition.egg-info/dependency_links.txt
urbandefinition.egg-info/entry_points.txt
urbandefinition.egg-info/requires.txt
urbandefinition.egg-info/top_level.txt