Metadata-Version: 1.0
Name: urbandefinition
Version: 0.3
Summary: Get Urban Dictionary definitions from the terminal
Home-page: https://github.com/dhamaniasad/urbandefinition
Author: Asad Dhamani
Author-email: dhamaniasad+code@gmail.com
License: Unlicense
Platform: UNKNOWN
